titleize/__init__.py
titleize/main.py
titleize-0.0.4.dist-info/LICENSE.txt
titleize-0.0.4.dist-info/METADATA
titleize-0.0.4.dist-info/WHEEL
titleize-0.0.4.dist-info/top_level.txt
titleize-0.0.4.dist-info/RECORD
