Metadata-Version: 2.1
Name: titleize
Version: 0.0.4
Summary: Convert Strings to Title Case
Home-page: https://github.com/TabulateJarl8/titleize
Author: Tabulate
Author-email: tabulatejarl8@gmail.com
License: UNKNOWN
Platform: UNKNOWN
Classifier: Programming Language :: Python :: 3
Classifier: License :: OSI Approved :: MIT License
Classifier: Operating System :: OS Independent
Requires-Python: >=3.6
Requires-Dist: nltk
